virtual/__init__.py
virtual/btrblocks_utils.py
virtual/data_handler.py
virtual/expr_optimizer.py
virtual/expr_parser.py
virtual/interface.py
virtual/io_utils.py
virtual/utils.py
virtual/v_compressor.py
virtual/v_driller.py
virtual/v_optimizer.py
virtual/v_reconstructor.py
virtual/v_size.py
virtualdb-0.1.0.dist-info/METADATA
virtualdb-0.1.0.dist-info/WHEEL
virtualdb-0.1.0.dist-info/top_level.txt
virtualdb-0.1.0.dist-info/RECORD
