Metadata-Version: 2.1
Name: virtualdb
Version: 0.1.0
Summary: Level up your Parquet file sizes!
Author-email: UTN Data Systems Lab <data-systems@utn.de>
Keywords: correlation-aware compression,semantic compression
Classifier: Programming Language :: Python :: 3
Classifier: License :: OSI Approved :: MIT License
Classifier: Operating System :: OS Independent
